volara/__init__.py
volara/cli.py
volara/datasets.py
volara/dbs.py
volara/logging.py
volara/lut.py
volara/py.typed
volara/tmp.py
volara/utils.py
volara/workers.py
volara/blockwise/__init__.py
volara/blockwise/aff_agglom.py
volara/blockwise/argmax.py
volara/blockwise/benchmark.py
volara/blockwise/blockwise.py
volara/blockwise/distance_agglom.py
volara/blockwise/extract_frags.py
volara/blockwise/graph_mws.py
volara/blockwise/pipeline.py
volara/blockwise/register.py
volara/blockwise/relabel.py
volara/blockwise/seeded_extract_frags.py
volara/blockwise/threshold.py
volara-1.0.2.dist-info/licenses/LICENSE
volara-1.0.2.dist-info/METADATA
volara-1.0.2.dist-info/WHEEL
volara-1.0.2.dist-info/entry_points.txt
volara-1.0.2.dist-info/top_level.txt
volara-1.0.2.dist-info/RECORD
