Metadata-Version: 2.4
Name: volara
Version: 1.0.2
Summary: A package for common blockwise computations for large microscopy volumes.
Author-email: William Patton <wllmpttn24@gmail.com>, Arlo Sheridan <arlo@e11.bio>
License: MIT
Classifier: Programming Language :: Python :: 3
Requires-Python: >=3.11
License-File: LICENSE
Requires-Dist: click>=8.0
Requires-Dist: daisy>=1.2.2
Requires-Dist: funlib.geometry>=0.3
Requires-Dist: funlib.persistence>=0.6
Requires-Dist: mwatershed>=0.5.2
Requires-Dist: pydantic>=2.6.3
Requires-Dist: numba>=0.59.0
Requires-Dist: scipy>=1.15.3
Requires-Dist: scikit-image>=0.25.2
Requires-Dist: polars>=1.31.0
Requires-Dist: psutil>=7.0.0
Provides-Extra: dev
Requires-Dist: pytest>=8.0; extra == "dev"
Requires-Dist: pytest-cov>=5.0; extra == "dev"
Requires-Dist: mypy>=1.0; extra == "dev"
Requires-Dist: ruff>=0.6; extra == "dev"
Provides-Extra: docs
Requires-Dist: autodoc_pydantic>=2.0; extra == "docs"
Requires-Dist: sphinx-autodoc-typehints>=2.0; extra == "docs"
Requires-Dist: sphinx-material>=0.0.36; extra == "docs"
Requires-Dist: sphinx-click>=6.0; extra == "docs"
Requires-Dist: myst-parser>=4.0; extra == "docs"
Requires-Dist: jupyter-sphinx>=0.5; extra == "docs"
Requires-Dist: matplotlib>=3.0; extra == "docs"
Requires-Dist: pooch>=1.8; extra == "docs"
Requires-Dist: wget>=3.2; extra == "docs"
Requires-Dist: funlib-show-neuroglancer>=0.2; extra == "docs"
Requires-Dist: nbsphinx>=0.9.7; extra == "docs"
Requires-Dist: jupytext>=1.16.7; extra == "docs"
Requires-Dist: pydata-sphinx-theme; extra == "docs"
Dynamic: license-file
